library/__init__.py
library/main.py
PythonCodes-0.0.1.dist-info/LICENCE
PythonCodes-0.0.1.dist-info/METADATA
PythonCodes-0.0.1.dist-info/WHEEL
PythonCodes-0.0.1.dist-info/top_level.txt
PythonCodes-0.0.1.dist-info/RECORD
