Metadata-Version: 2.1
Name: PythonCodes
Version: 0.0.1
Summary: PythonCodes
Author: Harry Gautam
Author-email: chharoonali786@gmail.com
Keywords: python,test,Codes,pythonCodes,AI
Classifier: Development Status :: 1 - Planning
Classifier: Intended Audience :: Developers
Classifier: Programming Language :: Python :: 3
Classifier: Operating System :: Unix
Classifier: Operating System :: MacOS :: MacOS X
Classifier: Operating System :: Microsoft :: Windows
License-File: LICENCE
